dbt_allure/__init__.py
dbt_allure/__main__.py
dbt_allure/configs.py
dbt_allure/parse.py
dbt_allure-0.0.1b2.dist-info/LICENSE
dbt_allure-0.0.1b2.dist-info/METADATA
dbt_allure-0.0.1b2.dist-info/WHEEL
dbt_allure-0.0.1b2.dist-info/RECORD
