Metadata-Version: 2.1
Name: dbt-allure
Version: 0.0.1b2
Summary: dbt-allure: Elevate dbt testing with intuitive Allure reports, streamlining data validation and transformation projects.
License: GPL-3.0-only
Author: Roman
Author-email: roman1001001@gmail.com
Requires-Python: >=3.9
Classifier: License :: OSI Approved :: GNU General Public License v3 (GPLv3)
Classifier: Programming Language :: Python :: 3
Classifier: Programming Language :: Python :: 3.9
Classifier: Programming Language :: Python :: 3.10
Classifier: Programming Language :: Python :: 3.11
Classifier: Programming Language :: Python :: 3.12
Requires-Dist: allure-python-commons (>=2.13.2,<3.0.0)
Requires-Dist: dbt-core (>=1.5)
Requires-Dist: jsonschema (>=4.21.1,<5.0.0)
Requires-Dist: pyyaml (>=6.0.1,<7.0.0)
